gedml/__init__.py
gedml/client/__init__.py
gedml/client/tmux/__init__.py
gedml/client/tmux/manager.py
gedml/config/__init__.py
gedml/config/setting/__init__.py
gedml/config/setting/core_setting.py
gedml/config/setting/launcher_setting.py
gedml/config/setting/recorder_setting.py
gedml/core/__init__.py
gedml/core/collectors/__init__.py
gedml/core/collectors/_default_global_collector.py
gedml/core/collectors/base_collector.py
gedml/core/collectors/default_collector.py
gedml/core/collectors/moco_collector.py
gedml/core/collectors/proxy_collector.py
gedml/core/datasets/__init__.py
gedml/core/datasets/base_dataset.py
gedml/core/datasets/cars196.py
gedml/core/datasets/cub200.py
gedml/core/datasets/imagenet.py
gedml/core/datasets/mini_imagenet.py
gedml/core/datasets/online_products.py
gedml/core/evaluators/__init__.py
gedml/core/evaluators/calculator.py
gedml/core/evaluators/calculator_mat.py
gedml/core/evaluators/metrics.py
gedml/core/losses/__init__.py
gedml/core/losses/base_loss.py
gedml/core/losses/classifier_based_loss/__init__.py
gedml/core/losses/classifier_based_loss/arcface_loss.py
gedml/core/losses/classifier_based_loss/cosface_loss.py
gedml/core/losses/classifier_based_loss/cross_entropy_loss.py
gedml/core/losses/classifier_based_loss/large_margin_softmax_loss.py
gedml/core/losses/pair_based_loss/__init__.py
gedml/core/losses/pair_based_loss/angular_loss.py
gedml/core/losses/pair_based_loss/circle_loss.py
gedml/core/losses/pair_based_loss/contrastive_loss.py
gedml/core/losses/pair_based_loss/fast_ap_loss.py
gedml/core/losses/pair_based_loss/lifted_structure_loss.py
gedml/core/losses/pair_based_loss/margin_loss.py
gedml/core/losses/pair_based_loss/multi_similarity_loss.py
gedml/core/losses/pair_based_loss/n_pair_loss.py
gedml/core/losses/pair_based_loss/pos_pair_loss.py
gedml/core/losses/pair_based_loss/signal_to_noise_ratio_loss.py
gedml/core/losses/pair_based_loss/triplet_loss.py
gedml/core/losses/proxy_based_loss/__init__.py
gedml-0.2.2.dist-info/LICENSE
gedml-0.2.2.dist-info/METADATA
gedml-0.2.2.dist-info/WHEEL
gedml-0.2.2.dist-info/top_level.txt
gedml-0.2.2.dist-info/RECORD
