Metadata-Version: 2.1
Name: gedml
Version: 0.2.2
Summary: GeDML is an easy-to-use generalized deep metric learning library,         which contains state-of-the-art deep metric learning algorithms and         auxiliary modules to build end-to-end compute vision systems
Home-page: https://github.com/zbr17/GeDML
Author: Borui Zhang
Author-email: zhang-br21@mails.tsinghua.edu.cn
License: UNKNOWN
Project-URL: Docs, https://zbr17.github.io/GeDML/
Platform: UNKNOWN
Classifier: Programming Language :: Python :: 3
Classifier: License :: OSI Approved :: MIT License
Classifier: Operating System :: OS Independent
Requires-Python: >=3.6
License-File: LICENSE
Requires-Dist: torch (>=1.7.0)
Requires-Dist: faiss-gpu (==1.5.3)
Requires-Dist: torchvision (>=0.8.0)
Requires-Dist: pretrainedmodels (>=0.7.4)
Requires-Dist: libtmux (>=0.8.5)
Requires-Dist: numpy (>=1.19.2)
Requires-Dist: tqdm (>=4.59.0)
Requires-Dist: pandas (>=1.1.3)
Requires-Dist: scipy (>=1.5.4)
Requires-Dist: scikit-learn (>=0.24.1)
Requires-Dist: tensorboard (>=2.4.0)
Requires-Dist: wandb (>=0.10.22)
Requires-Dist: timm (==0.3.2)
Requires-Dist: graphviz
Requires-Dist: torchdistlog
